LICENSE
MANIFEST.in
README.rst
requirements.txt
setup.cfg
setup.py
pygod/__init__.py
pygod/version.py
pygod.egg-info/PKG-INFO
pygod.egg-info/SOURCES.txt
pygod.egg-info/dependency_links.txt
pygod.egg-info/requires.txt
pygod.egg-info/top_level.txt
pygod/detector/__init__.py
pygod/detector/adone.py
pygod/detector/anomalous.py
pygod/detector/anomalydae.py
pygod/detector/base.py
pygod/detector/cola.py
pygod/detector/conad.py
pygod/detector/dominant.py
pygod/detector/done.py
pygod/detector/gaan.py
pygod/detector/gae.py
pygod/detector/guide.py
pygod/detector/ocgnn.py
pygod/detector/one.py
pygod/detector/radar.py
pygod/detector/scan.py
pygod/generator/__init__.py
pygod/generator/outlier_generator.py
pygod/metric/__init__.py
pygod/metric/metric.py
pygod/nn/__init__.py
pygod/nn/adone.py
pygod/nn/anomalydae.py
pygod/nn/cola.py
pygod/nn/conv.py
pygod/nn/decoder.py
pygod/nn/dominant.py
pygod/nn/done.py
pygod/nn/encoder.py
pygod/nn/functional.py
pygod/nn/gaan.py
pygod/nn/gae.py
pygod/nn/guide.py
pygod/nn/ocgnn.py
pygod/utils/__init__.py
pygod/utils/score_converter.py
pygod/utils/utility.py