Metadata-Version: 2.1
Name: pygod
Version: 1.0.0
Summary: A Python Library for Graph Outlier Detection (Anomaly Detection)
Home-page: https://github.com/pygod-team/pygod/
Download-URL: https://github.com/pygod-team/pygod/archive/main.zip
Author: PyGOD Team
Author-email: dev@pygod.org
License: BSD-2
Keywords: outlier detection,anomaly detection,graph mining,data mining,neural networks,graph neural networks
Classifier: Development Status :: 3 - Alpha
Classifier: Intended Audience :: Education
Classifier: Intended Audience :: Financial and Insurance Industry
Classifier: Intended Audience :: Science/Research
Classifier: Intended Audience :: Developers
Classifier: Intended Audience :: Information Technology
Classifier: License :: OSI Approved :: BSD License
Classifier: Programming Language :: Python :: 3.8
Classifier: Programming Language :: Python :: 3.9
Classifier: Programming Language :: Python :: 3.10
Classifier: Programming Language :: Python :: 3.11
Classifier: License :: OSI Approved :: BSD License
License-File: LICENSE
